kindling/__init__.py
kindling-0.0.0.dist-info/DESCRIPTION.rst
kindling-0.0.0.dist-info/METADATA
kindling-0.0.0.dist-info/RECORD
kindling-0.0.0.dist-info/WHEEL
kindling-0.0.0.dist-info/metadata.json
kindling-0.0.0.dist-info/top_level.txt
