Metadata-Version: 2.0
Name: kindling
Version: 0.0.0
Summary: Basic building blocks for pytorch.
Home-page: https://github.com/samuela/kindling
Author: Samuel Ainsworth
Author-email: skainsworth@gmail.com
License: UNKNOWN
Platform: UNKNOWN
